setup.py
pyminfraud/__init__.py
pyminfraud/compatibility.py
pyminfraud/documentation.py
pyminfraud/errors.py
pyminfraud/exceptions.py
pyminfraud/fields.py
pyminfraud/transform.py
pyminfraud/validate.py
pyminfraud.egg-info/PKG-INFO
pyminfraud.egg-info/SOURCES.txt
pyminfraud.egg-info/dependency_links.txt
pyminfraud.egg-info/pbr.json
pyminfraud.egg-info/top_level.txt