Metadata-Version: 1.1
Name: pyminfraud
Version: 1.0.4
Summary: ("Python library for interfacing with MaxMind's minFraud Web Service API.",)
Home-page: https://www.github.com/JDBurnZ/pyminfraud
Author: Joshua D. Burns
Author-email: joshuadburns@hotmail.com
License: pyminfraud by Joshua D. Burns is licensed under the Creative Commons Attribution
Download-URL: https://www.github.com/JDBurnZ/pyminfraud/tarball/1.0.3
Keywords: python maxmind minfraud pyminfraud
Platform: UNKNOWN
